faster_particles-0.3.0.dist-info/entry_points.txt
faster_particles-0.3.0.dist-info/DESCRIPTION.rst
faster_particles-0.3.0.dist-info/top_level.txt
faster_particles-0.3.0.dist-info/WHEEL
faster_particles-0.3.0.dist-info/METADATA
faster_particles-0.3.0.dist-info/metadata.json
faster_particles-0.3.0.dist-info/RECORD
bin/__init__.py
faster_particles/metrics.py
faster_particles/display_utils.py
faster_particles/clustering.py
faster_particles/uresnet.py
faster_particles/config.py
faster_particles/demo_ppn.py
faster_particles/ppn_utils.py
faster_particles/train_ppn.py
faster_particles/ppn.py
faster_particles/metrics_2d3d.py
faster_particles/__init__.py
faster_particles/base_net.py
faster_particles/test/test_ppn.py
faster_particles/test/__init__.py
faster_particles/bin/ppn.py
faster_particles/bin/__init__.py
faster_particles/toydata/toydata_generator.py
faster_particles/toydata/track_generator.py
faster_particles/toydata/__init__.py
faster_particles/toydata/shower_generator.py
faster_particles/base_net/uresnet.py
faster_particles/base_net/vgg.py
faster_particles/base_net/__init__.py
faster_particles/base_net/base_net.py
faster_particles/larcvdata/larcvdata_generator.py
faster_particles/larcvdata/__init__.py
