Metadata-Version: 2.0
Name: faster-particles
Version: 0.3.0
Summary: Point Proposal Network for particles images and related tools.
Home-page: https://github.com/Temigo/faster-particles
Author: Laura Domine, Ji Won Park, Kazuhiro Terao
Author-email: temigo@gmx.com
License: LICENSE.md
Project-URL: Source, https://github.com/Temigo/faster-particles
Project-URL: Bug Reports, https://github.com/Temigo/faster-particles/issues
Keywords: physics
Platform: UNKNOWN
Classifier: Development Status :: 3 - Alpha
Classifier: Environment :: Console
Classifier: Intended Audience :: Science/Research
Classifier: License :: OSI Approved :: MIT License
Classifier: Programming Language :: Python :: 2.7
Classifier: Topic :: Scientific/Engineering :: Physics
Classifier: Topic :: Scientific/Engineering :: Artificial Intelligence
Classifier: Topic :: Scientific/Engineering :: Image Recognition
Requires-Dist: matplotlib (>=2.2.2)
Requires-Dist: numpy (>=1.13.1)
Requires-Dist: scikit-learn (>=0.18.1)
Requires-Dist: scikit-image (>=0.12.3)
Requires-Dist: tensorflow (>=1.3.1)
